tempsentpolicy/__init__.py
tempsentpolicy/continous_time_series_cluster.py
tempsentpolicy/fine_tuning.py
tempsentpolicy/merging.py
tempsentpolicy-0.0.3.dist-info/METADATA
tempsentpolicy-0.0.3.dist-info/WHEEL
tempsentpolicy-0.0.3.dist-info/license.txt
tempsentpolicy-0.0.3.dist-info/top_level.txt
tempsentpolicy-0.0.3.dist-info/RECORD
