Metadata-Version: 2.1
Name: tempsentpolicy
Version: 0.0.3
Summary: Designed to ensure robust generalization across time stamps for sentiment analysis in policy-related texts
Author: Anonymous ACL SRW
Author-email: anonaclsrw@proton.me
Keywords: sentiment analysis,temporal,policy text,online text
Classifier: Development Status :: 1 - Planning
Classifier: Intended Audience :: Education
Classifier: Intended Audience :: Science/Research
Classifier: Programming Language :: Python :: 3
Classifier: Operating System :: Unix
Classifier: Operating System :: MacOS :: MacOS X
Classifier: Operating System :: Microsoft :: Windows
License-File: license.txt
Requires-Dist: matplotlib
Requires-Dist: ruptures
Requires-Dist: pandas
Requires-Dist: tqdm
Requires-Dist: torch
Requires-Dist: transformers
Requires-Dist: datasets
Requires-Dist: scikit-learn
Requires-Dist: numpy
